idrocalc/__init__.py
idrocalc/calc.py
idraulica_gregoriopascale-0.0.1.dist-info/LICENSE
idraulica_gregoriopascale-0.0.1.dist-info/METADATA
idraulica_gregoriopascale-0.0.1.dist-info/WHEEL
idraulica_gregoriopascale-0.0.1.dist-info/top_level.txt
idraulica_gregoriopascale-0.0.1.dist-info/RECORD
