Metadata-Version: 2.1
Name: idraulica-gregoriopascale
Version: 0.0.1
Summary: Modulo per la progettazione impianti idrico sanitari.
Home-page: https://github.com/pypa/idraulica
Author: pascale gregorio
Author-email: gregoriopascale@gmail.com
License: UNKNOWN
Platform: UNKNOWN
Classifier: Programming Language :: Python :: 3
Classifier: License :: OSI Approved :: MIT License
Classifier: Operating System :: OS Independent
Requires-Python: >=3.6
